Metadata-Version: 2.1
Name: eurmlsdk
Version: 0.1.204
Summary: eUR ML SDK
Author: eUR
Author-email: aiml@embedur.com
License: MIT
Classifier: Development Status :: 3 - Alpha
Classifier: License :: OSI Approved :: MIT License
Classifier: Programming Language :: Python :: 3
Classifier: Programming Language :: Python :: 3.7
License-File: LICENSE.txt
Requires-Dist: boto3
Requires-Dist: numpy==1.24.3
Requires-Dist: python-dotenv
Requires-Dist: paramiko
Requires-Dist: tensorflow==2.13.1
Requires-Dist: tqdm
Requires-Dist: ultralytics
Requires-Dist: torch
Requires-Dist: timm
Requires-Dist: torchvision
Requires-Dist: menpo
Requires-Dist: opencv-contrib-pythonnetron
